atom_runtime/__init__.py
atom_runtime/atom_config.py
atom_runtime/atom_controller.py
atom_runtime/logging.conf
atom_runtime/main.py
atom_runtime/atom_runtime_api/__init__.py
atom_runtime/atom_runtime_api/operator/__init__.py
atom_runtime/atom_runtime_api/operator/data_api.py
atom_runtime/atom_runtime_api/operator/model_info.py
atom_runtime/atom_runtime_api/operator/operators_api.py
atom_runtime/atom_runtime_api/operator/reasoning_api.py
atom_runtime/atom_runtime_api/operator/setup.py
atom_runtime/atom_runtime_api/operator/simple_runtime.py
atom_runtime/atom_runtime_api/operator/train_api.py
atom_runtime/connect/__init__.py
atom_runtime/connect/connnect.py
atom_runtime/connect/file_connect.py
atom_runtime/connect/hbase_conect.py
atom_runtime/connect/hdfs_connect.py
atom_runtime/connect/hdfs_contect.py
atom_runtime/connect/kafka_connect.py
atom_runtime/connect/kafka_contect.py
atom_runtime/connect/mysql_connect.py
atom_runtime/connect/mysql_contect.py
atom_runtime/connect/rocketmq_contect.py
atom_runtime/connect/s3_contect.py
atom_runtime/connect/cloud/__init__.py
atom_runtime/connect/cloud/aliyun_oss_contect.py
atom_runtime/dao/__init__.py
atom_runtime/dao/base_dao.py
atom_runtime/dao/port_dao.py
atom_runtime/data_set/__init__.py
atom_runtime/data_set/data_set.py
atom_runtime/data_set/field.py
atom_runtime/data_set/convert/__init__.py
atom_runtime/data_set/convert/convert.py
atom_runtime/data_set/convert/convert_mapper.py
atom_runtime/data_set/convert/csv_convert.py
atom_runtime/example/__init__.py
atom_runtime/example/reasoning_example.py
atom_runtime/example/train_example.py
atom_runtime/implement_code/__init__.py
atom_runtime/implement_code/code_byte.py
atom_runtime/implement_code/code_git.py
atom_runtime/implement_code/code_load.py
atom_runtime/implement_code/code_pip.py
atom_runtime/loggings/__init__.py
atom_runtime/loggings/atrom_logs.py
atom_runtime/operators/__init__.py
atom_runtime/operators/data_api_operator.py
atom_runtime/operators/data_code_operator.py
atom_runtime-0.0.20.dist-info/METADATA
atom_runtime-0.0.20.dist-info/WHEEL
atom_runtime-0.0.20.dist-info/entry_points.txt
atom_runtime-0.0.20.dist-info/top_level.txt
atom_runtime-0.0.20.dist-info/RECORD
