Metadata-Version: 2.1
Name: atom-runtime
Version: 0.0.20
Summary: atom runtime 
Home-page: https://github.com/githublaohu/atom
Author: laohu
Author-email: 2372554140@qq.com
License: Mulan PubL 2
Project-URL: Documentation, https://github.com/githublaohu/atom
Project-URL: Source, https://github.com/githublaohu/atom
Keywords: lamp,lampup,atom
Platform: UNKNOWN
Classifier: Topic :: Software Development :: Libraries :: Python Modules
Classifier: Operating System :: OS Independent
Classifier: Programming Language :: Python :: 3.6
Classifier: Programming Language :: Python :: 3.7
Requires-Dist: pandas
Requires-Dist: pydantic
Requires-Dist: pyyaml
Requires-Dist: nacos-sdk-python
Requires-Dist: gitpython
Requires-Dist: Flask
Requires-Dist: nvidia-ml-py
Requires-Dist: hdfs3
Requires-Dist: oss2
Requires-Dist: crcmod
Requires-Dist: pymysql
Requires-Dist: happybase
Requires-Dist: mysql-connector
